[
  {
    "device_id": "DEV_001",
    "timestamp": "2026-06-01T00:00:00",
    "temperature": 50.42,
    "battery": 61.25,
    "signal_strength": -67.94
  },
  {
    "device_id": "DEV_001",
    "timestamp": "2026-06-01T00:05:00",
    "temperature": 51.6,
    "battery": 60.59,
    "signal_strength": -68.41
  },
  {
    "device_id": "DEV_001",
    "timestamp": "2026-06-01T00:10:00",
    "temperature": 50.19,
    "battery": 60.14,
    "signal_strength": -68.38
  },
  {
    "device_id": "DEV_001",
    "timestamp": "2026-06-01T00:15:00",
    "temperature": 48.77,
    "battery": 59.66,
    "signal_strength": -67.48
  },
  {
    "device_id": "DEV_001",
    "timestamp": "2026-06-01T00:20:00",
    "temperature": 48.9,
    "battery": 59.21,
    "signal_strength": -66.94
  },
  {
    "device_id": "DEV_001",
    "timestamp": "2026-06-01T00:25:00",
    "temperature": 49.83,
    "battery": 58.42,
    "signal_strength": -65.11
  },
  {
    "device_id": "DEV_001",
    "timestamp": "2026-06-01T00:30:00",
    "temperature": 50.42,
    "battery": 58.16,
    "signal_strength": -67.18
  },
  {
    "device_id": "DEV_001",
    "timestamp": "2026-06-01T00:35:00",
    "temperature": 51.79,
    "battery": 57.9,
    "signal_strength": -69.62
  },
  {
    "device_id": "DEV_001",
    "timestamp": "2026-06-01T00:40:00",
    "temperature": 50.58,
    "battery": 58.46,
    "signal_strength": -69.0
  },
  {
    "device_id": "DEV_001",
    "timestamp": "2026-06-01T00:45:00",
    "temperature": 51.5,
    "battery": 58.83,
    "signal_strength": -68.78
  },
  {
    "device_id": "DEV_001",
    "timestamp": "2026-06-01T00:50:00",
    "temperature": 52.92,
    "battery": 58.64,
    "signal_strength": -68.47
  },
  {
    "device_id": "DEV_001",
    "timestamp": "2026-06-01T00:55:00",
    "temperature": 53.91,
    "battery": 58.83,
    "signal_strength": -66.3
  },
  {
    "device_id": "DEV_001",
    "timestamp": "2026-06-01T01:00:00",
    "temperature": 54.14,
    "battery": 59.16,
    "signal_strength": -69.03
  },
  {
    "device_id": "DEV_001",
    "timestamp": "2026-06-01T01:05:00",
    "temperature": 53.32,
    "battery": 58.82,
    "signal_strength": -71.55
  },
  {
    "device_id": "DEV_001",
    "timestamp": "2026-06-01T01:10:00",
    "temperature": 52.52,
    "battery": 58.18,
    "signal_strength": -72.88
  },
  {
    "device_id": "DEV_001",
    "timestamp": "2026-06-01T01:15:00",
    "temperature": 52.93,
    "battery": 57.96,
    "signal_strength": -73.66
  },
  {
    "device_id": "DEV_001",
    "timestamp": "2026-06-01T01:20:00",
    "temperature": 52.06,
    "battery": 57.59,
    "signal_strength": -71.04
  },
  {
    "device_id": "DEV_001",
    "timestamp": "2026-06-01T01:25:00",
    "temperature": 52.5,
    "battery": 57.76,
    "signal_strength": -73.01
  },
  {
    "device_id": "DEV_001",
    "timestamp": "2026-06-01T01:30:00",
    "temperature": 53.19,
    "battery": 57.22,
    "signal_strength": -73.73
  },
  {
    "device_id": "DEV_001",
    "timestamp": "2026-06-01T01:35:00",
    "temperature": 54.66,
    "battery": 57.44,
    "signal_strength": -73.39
  },
  {
    "device_id": "DEV_001",
    "timestamp": "2026-06-01T01:40:00",
    "temperature": 55.21,
    "battery": 57.99,
    "signal_strength": -71.73
  },
  {
    "device_id": "DEV_001",
    "timestamp": "2026-06-01T01:45:00",
    "temperature": 54.4,
    "battery": 57.24,
    "signal_strength": -72.84
  },
  {
    "device_id": "DEV_001",
    "timestamp": "2026-06-01T01:50:00",
    "temperature": 53.7,
    "battery": 56.78,
    "signal_strength": -70.18
  },
  {
    "device_id": "DEV_001",
    "timestamp": "2026-06-01T01:55:00",
    "temperature": 54.83,
    "battery": 56.48,
    "signal_strength": -69.25
  },
  {
    "device_id": "DEV_001",
    "timestamp": "2026-06-01T02:00:00",
    "temperature": 54.52,
    "battery": 57.14,
    "signal_strength": -69.5
  },
  {
    "device_id": "DEV_001",
    "timestamp": "2026-06-01T02:05:00",
    "temperature": 53.81,
    "battery": 56.73,
    "signal_strength": -69.13
  },
  {
    "device_id": "DEV_001",
    "timestamp": "2026-06-01T02:10:00",
    "temperature": 53.1,
    "battery": 56.87,
    "signal_strength": -66.74
  },
  {
    "device_id": "DEV_001",
    "timestamp": "2026-06-01T02:15:00",
    "temperature": 52.8,
    "battery": 56.42,
    "signal_strength": -63.75
  },
  {
    "device_id": "DEV_001",
    "timestamp": "2026-06-01T02:20:00",
    "temperature": 52.83,
    "battery": 55.77,
    "signal_strength": -66.47
  },
  {
    "device_id": "DEV_001",
    "timestamp": "2026-06-01T02:25:00",
    "temperature": 51.66,
    "battery": 55.97,
    "signal_strength": -64.72
  },
  {
    "device_id": "DEV_001",
    "timestamp": "2026-06-01T02:30:00",
    "temperature": 51.43,
    "battery": 55.27,
    "signal_strength": -65.43
  },
  {
    "device_id": "DEV_001",
    "timestamp": "2026-06-01T02:35:00",
    "temperature": 52.92,
    "battery": 55.32,
    "signal_strength": -62.6
  },
  {
    "device_id": "DEV_001",
    "timestamp": "2026-06-01T02:40:00",
    "temperature": 54.0,
    "battery": 54.54,
    "signal_strength": -61.28
  },
  {
    "device_id": "DEV_001",
    "timestamp": "2026-06-01T02:45:00",
    "temperature": 54.55,
    "battery": 54.6,
    "signal_strength": -62.68
  },
  {
    "device_id": "DEV_001",
    "timestamp": "2026-06-01T02:50:00",
    "temperature": 54.97,
    "battery": 53.98,
    "signal_strength": -63.07
  },
  {
    "device_id": "DEV_001",
    "timestamp": "2026-06-01T02:55:00",
    "temperature": 54.83,
    "battery": 54.71,
    "signal_strength": -60.81
  },
  {
    "device_id": "DEV_001",
    "timestamp": "2026-06-01T03:00:00",
    "temperature": 54.12,
    "battery": 54.71,
    "signal_strength": -62.74
  },
  {
    "device_id": "DEV_001",
    "timestamp": "2026-06-01T03:05:00",
    "temperature": 55.36,
    "battery": 55.3,
    "signal_strength": -63.95
  },
  {
    "device_id": "DEV_001",
    "timestamp": "2026-06-01T03:10:00",
    "temperature": 55.78,
    "battery": 55.47,
    "signal_strength": -66.03
  },
  {
    "device_id": "DEV_001",
    "timestamp": "2026-06-01T03:15:00",
    "temperature": 56.57,
    "battery": 55.53,
    "signal_strength": -64.36
  },
  {
    "device_id": "DEV_002",
    "timestamp": "2026-06-01T00:00:00",
    "temperature": 44.14,
    "battery": 60.71,
    "signal_strength": -64.76
  },
  {
    "device_id": "DEV_002",
    "timestamp": "2026-06-01T00:05:00",
    "temperature": 45.13,
    "battery": 60.4,
    "signal_strength": -67.41
  },
  {
    "device_id": "DEV_002",
    "timestamp": "2026-06-01T00:10:00",
    "temperature": 46.26,
    "battery": 61.12,
    "signal_strength": -69.9
  },
  {
    "device_id": "DEV_002",
    "timestamp": "2026-06-01T00:15:00",
    "temperature": 46.22,
    "battery": 60.43,
    "signal_strength": -68.34
  },
  {
    "device_id": "DEV_002",
    "timestamp": "2026-06-01T00:20:00",
    "temperature": 47.02,
    "battery": 59.84,
    "signal_strength": -68.49
  },
  {
    "device_id": "DEV_002",
    "timestamp": "2026-06-01T00:25:00",
    "temperature": 47.17,
    "battery": 59.46,
    "signal_strength": -66.26
  },
  {
    "device_id": "DEV_002",
    "timestamp": "2026-06-01T00:30:00",
    "temperature": 46.94,
    "battery": 59.0,
    "signal_strength": -66.02
  },
  {
    "device_id": "DEV_002",
    "timestamp": "2026-06-01T00:35:00",
    "temperature": 47.63,
    "battery": 58.52,
    "signal_strength": -67.15
  },
  {
    "device_id": "DEV_002",
    "timestamp": "2026-06-01T00:40:00",
    "temperature": 49.12,
    "battery": 58.76,
    "signal_strength": -67.52
  },
  {
    "device_id": "DEV_002",
    "timestamp": "2026-06-01T00:45:00",
    "temperature": 49.17,
    "battery": 58.15,
    "signal_strength": -69.17
  },
  {
    "device_id": "DEV_002",
    "timestamp": "2026-06-01T00:50:00",
    "temperature": 48.68,
    "battery": 58.29,
    "signal_strength": -70.79
  },
  {
    "device_id": "DEV_002",
    "timestamp": "2026-06-01T00:55:00",
    "temperature": 47.84,
    "battery": 57.6,
    "signal_strength": -70.0
  },
  {
    "device_id": "DEV_002",
    "timestamp": "2026-06-01T01:00:00",
    "temperature": 47.03,
    "battery": 58.25,
    "signal_strength": -67.84
  },
  {
    "device_id": "DEV_002",
    "timestamp": "2026-06-01T01:05:00",
    "temperature": 45.74,
    "battery": 57.83,
    "signal_strength": -66.83
  },
  {
    "device_id": "DEV_002",
    "timestamp": "2026-06-01T01:10:00",
    "temperature": 44.88,
    "battery": 57.24,
    "signal_strength": -64.22
  },
  {
    "device_id": "DEV_002",
    "timestamp": "2026-06-01T01:15:00",
    "temperature": 45.09,
    "battery": 57.2,
    "signal_strength": -62.51
  },
  {
    "device_id": "DEV_002",
    "timestamp": "2026-06-01T01:20:00",
    "temperature": 46.01,
    "battery": 56.7,
    "signal_strength": -64.93
  },
  {
    "device_id": "DEV_002",
    "timestamp": "2026-06-01T01:25:00",
    "temperature": 45.8,
    "battery": 56.58,
    "signal_strength": -65.13
  },
  {
    "device_id": "DEV_002",
    "timestamp": "2026-06-01T01:30:00",
    "temperature": 46.49,
    "battery": 56.86,
    "signal_strength": -62.23
  },
  {
    "device_id": "DEV_002",
    "timestamp": "2026-06-01T01:35:00",
    "temperature": 45.29,
    "battery": 56.7,
    "signal_strength": -63.19
  },
  {
    "device_id": "DEV_002",
    "timestamp": "2026-06-01T01:40:00",
    "temperature": 46.38,
    "battery": 56.3,
    "signal_strength": -65.05
  },
  {
    "device_id": "DEV_002",
    "timestamp": "2026-06-01T01:45:00",
    "temperature": 46.23,
    "battery": 56.18,
    "signal_strength": -66.38
  },
  {
    "device_id": "DEV_002",
    "timestamp": "2026-06-01T01:50:00",
    "temperature": 45.48,
    "battery": 56.86,
    "signal_strength": -66.72
  },
  {
    "device_id": "DEV_002",
    "timestamp": "2026-06-01T01:55:00",
    "temperature": 46.56,
    "battery": 56.94,
    "signal_strength": -69.42
  },
  {
    "device_id": "DEV_002",
    "timestamp": "2026-06-01T02:00:00",
    "temperature": 48.06,
    "battery": 57.48,
    "signal_strength": -66.61
  },
  {
    "device_id": "DEV_002",
    "timestamp": "2026-06-01T02:05:00",
    "temperature": 49.34,
    "battery": 58.04,
    "signal_strength": -68.61
  },
  {
    "device_id": "DEV_002",
    "timestamp": "2026-06-01T02:10:00",
    "temperature": 49.3,
    "battery": 57.58,
    "signal_strength": -69.2
  },
  {
    "device_id": "DEV_002",
    "timestamp": "2026-06-01T02:15:00",
    "temperature": 47.98,
    "battery": 57.39,
    "signal_strength": -66.29
  },
  {
    "device_id": "DEV_002",
    "timestamp": "2026-06-01T02:20:00",
    "temperature": 47.28,
    "battery": 57.84,
    "signal_strength": -66.56
  },
  {
    "device_id": "DEV_002",
    "timestamp": "2026-06-01T02:25:00",
    "temperature": 47.05,
    "battery": 58.57,
    "signal_strength": -63.59
  },
  {
    "device_id": "DEV_002",
    "timestamp": "2026-06-01T02:30:00",
    "temperature": 47.22,
    "battery": 58.92,
    "signal_strength": -65.66
  },
  {
    "device_id": "DEV_002",
    "timestamp": "2026-06-01T02:35:00",
    "temperature": 46.61,
    "battery": 59.67,
    "signal_strength": -65.18
  },
  {
    "device_id": "DEV_002",
    "timestamp": "2026-06-01T02:40:00",
    "temperature": 46.74,
    "battery": 60.07,
    "signal_strength": -67.84
  },
  {
    "device_id": "DEV_002",
    "timestamp": "2026-06-01T02:45:00",
    "temperature": 46.99,
    "battery": 60.07,
    "signal_strength": -65.72
  },
  {
    "device_id": "DEV_002",
    "timestamp": "2026-06-01T02:50:00",
    "temperature": 45.96,
    "battery": 60.81,
    "signal_strength": -68.24
  },
  {
    "device_id": "DEV_002",
    "timestamp": "2026-06-01T02:55:00",
    "temperature": 45.02,
    "battery": 60.96,
    "signal_strength": -67.19
  },
  {
    "device_id": "DEV_002",
    "timestamp": "2026-06-01T03:00:00",
    "temperature": 44.23,
    "battery": 60.35,
    "signal_strength": -64.85
  },
  {
    "device_id": "DEV_002",
    "timestamp": "2026-06-01T03:05:00",
    "temperature": 43.47,
    "battery": 60.5,
    "signal_strength": -64.13
  },
  {
    "device_id": "DEV_002",
    "timestamp": "2026-06-01T03:10:00",
    "temperature": 43.23,
    "battery": 60.63,
    "signal_strength": -63.99
  },
  {
    "device_id": "DEV_002",
    "timestamp": "2026-06-01T03:15:00",
    "temperature": 44.53,
    "battery": 60.16,
    "signal_strength": -62.69
  },
  {
    "device_id": "DEV_003",
    "timestamp": "2026-06-01T00:00:00",
    "temperature": 29.81,
    "battery": 73.56,
    "signal_strength": -51.62
  },
  {
    "device_id": "DEV_003",
    "timestamp": "2026-06-01T00:05:00",
    "temperature": 28.53,
    "battery": 73.49,
    "signal_strength": -48.63
  },
  {
    "device_id": "DEV_003",
    "timestamp": "2026-06-01T00:10:00",
    "temperature": 30.02,
    "battery": 72.81,
    "signal_strength": -50.35
  },
  {
    "device_id": "DEV_003",
    "timestamp": "2026-06-01T00:15:00",
    "temperature": 29.32,
    "battery": 73.5,
    "signal_strength": -48.06
  },
  {
    "device_id": "DEV_003",
    "timestamp": "2026-06-01T00:20:00",
    "temperature": 30.46,
    "battery": 73.29,
    "signal_strength": -50.11
  },
  {
    "device_id": "DEV_003",
    "timestamp": "2026-06-01T00:25:00",
    "temperature": 31.46,
    "battery": 73.62,
    "signal_strength": -49.44
  },
  {
    "device_id": "DEV_003",
    "timestamp": "2026-06-01T00:30:00",
    "temperature": 32.92,
    "battery": 73.87,
    "signal_strength": -52.39
  },
  {
    "device_id": "DEV_003",
    "timestamp": "2026-06-01T00:35:00",
    "temperature": 33.87,
    "battery": 73.55,
    "signal_strength": -51.41
  },
  {
    "device_id": "DEV_003",
    "timestamp": "2026-06-01T00:40:00",
    "temperature": 35.19,
    "battery": 72.96,
    "signal_strength": -53.72
  },
  {
    "device_id": "DEV_003",
    "timestamp": "2026-06-01T00:45:00",
    "temperature": 34.01,
    "battery": 73.05,
    "signal_strength": -55.09
  },
  {
    "device_id": "DEV_003",
    "timestamp": "2026-06-01T00:50:00",
    "temperature": 34.32,
    "battery": 73.4,
    "signal_strength": -56.87
  },
  {
    "device_id": "DEV_003",
    "timestamp": "2026-06-01T00:55:00",
    "temperature": 34.72,
    "battery": 73.02,
    "signal_strength": -56.94
  },
  {
    "device_id": "DEV_003",
    "timestamp": "2026-06-01T01:00:00",
    "temperature": 35.94,
    "battery": 73.57,
    "signal_strength": -59.39
  },
  {
    "device_id": "DEV_003",
    "timestamp": "2026-06-01T01:05:00",
    "temperature": 35.71,
    "battery": 73.21,
    "signal_strength": -62.37
  },
  {
    "device_id": "DEV_003",
    "timestamp": "2026-06-01T01:10:00",
    "temperature": 36.52,
    "battery": 73.43,
    "signal_strength": -63.8
  },
  {
    "device_id": "DEV_003",
    "timestamp": "2026-06-01T01:15:00",
    "temperature": 37.24,
    "battery": 73.51,
    "signal_strength": -64.23
  },
  {
    "device_id": "DEV_003",
    "timestamp": "2026-06-01T01:20:00",
    "temperature": 35.77,
    "battery": 72.83,
    "signal_strength": -61.93
  },
  {
    "device_id": "DEV_003",
    "timestamp": "2026-06-01T01:25:00",
    "temperature": 36.98,
    "battery": 72.9,
    "signal_strength": -59.92
  },
  {
    "device_id": "DEV_003",
    "timestamp": "2026-06-01T01:30:00",
    "temperature": 37.23,
    "battery": 72.34,
    "signal_strength": -62.16
  },
  {
    "device_id": "DEV_003",
    "timestamp": "2026-06-01T01:35:00",
    "temperature": 36.65,
    "battery": 72.98,
    "signal_strength": -60.38
  },
  {
    "device_id": "DEV_003",
    "timestamp": "2026-06-01T01:40:00",
    "temperature": 37.73,
    "battery": 73.62,
    "signal_strength": -62.12
  },
  {
    "device_id": "DEV_003",
    "timestamp": "2026-06-01T01:45:00",
    "temperature": 36.98,
    "battery": 72.98,
    "signal_strength": -60.44
  },
  {
    "device_id": "DEV_003",
    "timestamp": "2026-06-01T01:50:00",
    "temperature": 38.13,
    "battery": 72.83,
    "signal_strength": -59.72
  },
  {
    "device_id": "DEV_003",
    "timestamp": "2026-06-01T01:55:00",
    "temperature": 37.09,
    "battery": 73.52,
    "signal_strength": -57.53
  },
  {
    "device_id": "DEV_003",
    "timestamp": "2026-06-01T02:00:00",
    "temperature": 38.52,
    "battery": 74.02,
    "signal_strength": -55.24
  },
  {
    "device_id": "DEV_003",
    "timestamp": "2026-06-01T02:05:00",
    "temperature": 37.09,
    "battery": 74.4,
    "signal_strength": -56.25
  },
  {
    "device_id": "DEV_003",
    "timestamp": "2026-06-01T02:10:00",
    "temperature": 38.38,
    "battery": 74.88,
    "signal_strength": -54.07
  },
  {
    "device_id": "DEV_003",
    "timestamp": "2026-06-01T02:15:00",
    "temperature": 39.31,
    "battery": 74.51,
    "signal_strength": -52.35
  },
  {
    "device_id": "DEV_003",
    "timestamp": "2026-06-01T02:20:00",
    "temperature": 38.13,
    "battery": 75.11,
    "signal_strength": -50.2
  },
  {
    "device_id": "DEV_003",
    "timestamp": "2026-06-01T02:25:00",
    "temperature": 37.3,
    "battery": 75.62,
    "signal_strength": -50.44
  },
  {
    "device_id": "DEV_003",
    "timestamp": "2026-06-01T02:30:00",
    "temperature": 36.72,
    "battery": 76.09,
    "signal_strength": -52.07
  },
  {
    "device_id": "DEV_003",
    "timestamp": "2026-06-01T02:35:00",
    "temperature": 35.29,
    "battery": 75.6,
    "signal_strength": -53.1
  },
  {
    "device_id": "DEV_003",
    "timestamp": "2026-06-01T02:40:00",
    "temperature": 36.38,
    "battery": 76.35,
    "signal_strength": -54.43
  },
  {
    "device_id": "DEV_003",
    "timestamp": "2026-06-01T02:45:00",
    "temperature": 36.8,
    "battery": 76.19,
    "signal_strength": -51.54
  },
  {
    "device_id": "DEV_003",
    "timestamp": "2026-06-01T02:50:00",
    "temperature": 36.91,
    "battery": 76.89,
    "signal_strength": -53.85
  },
  {
    "device_id": "DEV_003",
    "timestamp": "2026-06-01T02:55:00",
    "temperature": 38.32,
    "battery": 76.38,
    "signal_strength": -51.07
  },
  {
    "device_id": "DEV_003",
    "timestamp": "2026-06-01T03:00:00",
    "temperature": 37.62,
    "battery": 75.75,
    "signal_strength": -51.46
  },
  {
    "device_id": "DEV_003",
    "timestamp": "2026-06-01T03:05:00",
    "temperature": 38.31,
    "battery": 75.45,
    "signal_strength": -50.82
  },
  {
    "device_id": "DEV_003",
    "timestamp": "2026-06-01T03:10:00",
    "temperature": 38.34,
    "battery": 75.27,
    "signal_strength": -50.36
  },
  {
    "device_id": "DEV_003",
    "timestamp": "2026-06-01T03:15:00",
    "temperature": 37.6,
    "battery": 75.6,
    "signal_strength": -53.35
  },
  {
    "device_id": "DEV_004",
    "timestamp": "2026-06-01T00:00:00",
    "temperature": 66.86,
    "battery": 79.12,
    "signal_strength": -52.04
  },
  {
    "device_id": "DEV_004",
    "timestamp": "2026-06-01T00:05:00",
    "temperature": 65.57,
    "battery": 79.38,
    "signal_strength": -53.06
  },
  {
    "device_id": "DEV_004",
    "timestamp": "2026-06-01T00:10:00",
    "temperature": 65.01,
    "battery": 79.94,
    "signal_strength": -51.74
  },
  {
    "device_id": "DEV_004",
    "timestamp": "2026-06-01T00:15:00",
    "temperature": 64.41,
    "battery": 79.63,
    "signal_strength": -52.29
  },
  {
    "device_id": "DEV_004",
    "timestamp": "2026-06-01T00:20:00",
    "temperature": 64.12,
    "battery": 79.3,
    "signal_strength": -54.53
  },
  {
    "device_id": "DEV_004",
    "timestamp": "2026-06-01T00:25:00",
    "temperature": 63.88,
    "battery": 80.0,
    "signal_strength": -53.47
  },
  {
    "device_id": "DEV_004",
    "timestamp": "2026-06-01T00:30:00",
    "temperature": 65.09,
    "battery": 80.18,
    "signal_strength": -54.66
  },
  {
    "device_id": "DEV_004",
    "timestamp": "2026-06-01T00:35:00",
    "temperature": 65.23,
    "battery": 79.38,
    "signal_strength": -55.94
  },
  {
    "device_id": "DEV_004",
    "timestamp": "2026-06-01T00:40:00",
    "temperature": 65.02,
    "battery": 79.51,
    "signal_strength": -55.01
  },
  {
    "device_id": "DEV_004",
    "timestamp": "2026-06-01T00:45:00",
    "temperature": 64.91,
    "battery": 79.42,
    "signal_strength": -56.73
  },
  {
    "device_id": "DEV_004",
    "timestamp": "2026-06-01T00:50:00",
    "temperature": 64.83,
    "battery": 80.06,
    "signal_strength": -54.95
  },
  {
    "device_id": "DEV_004",
    "timestamp": "2026-06-01T00:55:00",
    "temperature": 63.84,
    "battery": 79.4,
    "signal_strength": -54.86
  },
  {
    "device_id": "DEV_004",
    "timestamp": "2026-06-01T01:00:00",
    "temperature": 64.24,
    "battery": 79.14,
    "signal_strength": -52.95
  },
  {
    "device_id": "DEV_004",
    "timestamp": "2026-06-01T01:05:00",
    "temperature": 64.99,
    "battery": 79.42,
    "signal_strength": -54.6
  },
  {
    "device_id": "DEV_004",
    "timestamp": "2026-06-01T01:10:00",
    "temperature": 64.09,
    "battery": 78.66,
    "signal_strength": -56.13
  },
  {
    "device_id": "DEV_004",
    "timestamp": "2026-06-01T01:15:00",
    "temperature": 64.02,
    "battery": 79.22,
    "signal_strength": -58.69
  },
  {
    "device_id": "DEV_004",
    "timestamp": "2026-06-01T01:20:00",
    "temperature": 63.76,
    "battery": 79.43,
    "signal_strength": -60.52
  },
  {
    "device_id": "DEV_004",
    "timestamp": "2026-06-01T01:25:00",
    "temperature": 64.35,
    "battery": 79.42,
    "signal_strength": -62.06
  },
  {
    "device_id": "DEV_004",
    "timestamp": "2026-06-01T01:30:00",
    "temperature": 64.82,
    "battery": 78.63,
    "signal_strength": -60.55
  },
  {
    "device_id": "DEV_004",
    "timestamp": "2026-06-01T01:35:00",
    "temperature": 65.63,
    "battery": 78.0,
    "signal_strength": -61.0
  },
  {
    "device_id": "DEV_004",
    "timestamp": "2026-06-01T01:40:00",
    "temperature": 64.66,
    "battery": 78.73,
    "signal_strength": -60.89
  },
  {
    "device_id": "DEV_004",
    "timestamp": "2026-06-01T01:45:00",
    "temperature": 63.31,
    "battery": 78.33,
    "signal_strength": -58.8
  },
  {
    "device_id": "DEV_004",
    "timestamp": "2026-06-01T01:50:00",
    "temperature": 63.18,
    "battery": 78.81,
    "signal_strength": -57.79
  },
  {
    "device_id": "DEV_004",
    "timestamp": "2026-06-01T01:55:00",
    "temperature": 64.64,
    "battery": 78.96,
    "signal_strength": -55.09
  },
  {
    "device_id": "DEV_004",
    "timestamp": "2026-06-01T02:00:00",
    "temperature": 65.81,
    "battery": 79.14,
    "signal_strength": -53.77
  },
  {
    "device_id": "DEV_004",
    "timestamp": "2026-06-01T02:05:00",
    "temperature": 65.82,
    "battery": 79.67,
    "signal_strength": -53.48
  },
  {
    "device_id": "DEV_004",
    "timestamp": "2026-06-01T02:10:00",
    "temperature": 67.01,
    "battery": 80.06,
    "signal_strength": -53.63
  },
  {
    "device_id": "DEV_004",
    "timestamp": "2026-06-01T02:15:00",
    "temperature": 66.29,
    "battery": 79.66,
    "signal_strength": -52.8
  },
  {
    "device_id": "DEV_004",
    "timestamp": "2026-06-01T02:20:00",
    "temperature": 67.09,
    "battery": 79.69,
    "signal_strength": -52.04
  },
  {
    "device_id": "DEV_004",
    "timestamp": "2026-06-01T02:25:00",
    "temperature": 66.41,
    "battery": 79.01,
    "signal_strength": -53.33
  },
  {
    "device_id": "DEV_004",
    "timestamp": "2026-06-01T02:30:00",
    "temperature": 65.73,
    "battery": 78.72,
    "signal_strength": -53.09
  },
  {
    "device_id": "DEV_004",
    "timestamp": "2026-06-01T02:35:00",
    "temperature": 64.65,
    "battery": 78.29,
    "signal_strength": -51.93
  },
  {
    "device_id": "DEV_004",
    "timestamp": "2026-06-01T02:40:00",
    "temperature": 65.27,
    "battery": 77.59,
    "signal_strength": -52.48
  },
  {
    "device_id": "DEV_004",
    "timestamp": "2026-06-01T02:45:00",
    "temperature": 65.4,
    "battery": 77.46,
    "signal_strength": -54.24
  },
  {
    "device_id": "DEV_004",
    "timestamp": "2026-06-01T02:50:00",
    "temperature": 65.16,
    "battery": 78.11,
    "signal_strength": -53.74
  },
  {
    "device_id": "DEV_004",
    "timestamp": "2026-06-01T02:55:00",
    "temperature": 65.75,
    "battery": 78.68,
    "signal_strength": -52.15
  },
  {
    "device_id": "DEV_004",
    "timestamp": "2026-06-01T03:00:00",
    "temperature": 65.39,
    "battery": 77.89,
    "signal_strength": -53.04
  },
  {
    "device_id": "DEV_004",
    "timestamp": "2026-06-01T03:05:00",
    "temperature": 66.15,
    "battery": 78.46,
    "signal_strength": -50.32
  },
  {
    "device_id": "DEV_004",
    "timestamp": "2026-06-01T03:10:00",
    "temperature": 65.91,
    "battery": 78.86,
    "signal_strength": -50.04
  },
  {
    "device_id": "DEV_004",
    "timestamp": "2026-06-01T03:15:00",
    "temperature": 66.22,
    "battery": 78.41,
    "signal_strength": -51.72
  },
  {
    "device_id": "DEV_005",
    "timestamp": "2026-06-01T00:00:00",
    "temperature": 41.2,
    "battery": 60.86,
    "signal_strength": -68.56
  },
  {
    "device_id": "DEV_005",
    "timestamp": "2026-06-01T00:05:00",
    "temperature": 41.1,
    "battery": 60.26,
    "signal_strength": -67.83
  },
  {
    "device_id": "DEV_005",
    "timestamp": "2026-06-01T00:10:00",
    "temperature": 39.68,
    "battery": 60.09,
    "signal_strength": -67.44
  },
  {
    "device_id": "DEV_005",
    "timestamp": "2026-06-01T00:15:00",
    "temperature": 38.26,
    "battery": 60.32,
    "signal_strength": -69.63
  },
  {
    "device_id": "DEV_005",
    "timestamp": "2026-06-01T00:20:00",
    "temperature": 38.15,
    "battery": 59.6,
    "signal_strength": -70.36
  },
  {
    "device_id": "DEV_005",
    "timestamp": "2026-06-01T00:25:00",
    "temperature": 37.28,
    "battery": 59.32,
    "signal_strength": -68.79
  },
  {
    "device_id": "DEV_005",
    "timestamp": "2026-06-01T00:30:00",
    "temperature": 36.92,
    "battery": 59.72,
    "signal_strength": -66.8
  },
  {
    "device_id": "DEV_005",
    "timestamp": "2026-06-01T00:35:00",
    "temperature": 36.18,
    "battery": 59.05,
    "signal_strength": -69.68
  },
  {
    "device_id": "DEV_005",
    "timestamp": "2026-06-01T00:40:00",
    "temperature": 36.3,
    "battery": 59.85,
    "signal_strength": -70.58
  },
  {
    "device_id": "DEV_005",
    "timestamp": "2026-06-01T00:45:00",
    "temperature": 36.75,
    "battery": 60.3,
    "signal_strength": -69.67
  },
  {
    "device_id": "DEV_005",
    "timestamp": "2026-06-01T00:50:00",
    "temperature": 37.51,
    "battery": 61.02,
    "signal_strength": -71.47
  },
  {
    "device_id": "DEV_005",
    "timestamp": "2026-06-01T00:55:00",
    "temperature": 36.07,
    "battery": 60.46,
    "signal_strength": -73.71
  },
  {
    "device_id": "DEV_005",
    "timestamp": "2026-06-01T01:00:00",
    "temperature": 36.58,
    "battery": 60.56,
    "signal_strength": -75.4
  },
  {
    "device_id": "DEV_005",
    "timestamp": "2026-06-01T01:05:00",
    "temperature": 37.18,
    "battery": 60.99,
    "signal_strength": -77.39
  },
  {
    "device_id": "DEV_005",
    "timestamp": "2026-06-01T01:10:00",
    "temperature": 37.5,
    "battery": 61.39,
    "signal_strength": -79.7
  },
  {
    "device_id": "DEV_005",
    "timestamp": "2026-06-01T01:15:00",
    "temperature": 38.46,
    "battery": 62.13,
    "signal_strength": -82.05
  },
  {
    "device_id": "DEV_005",
    "timestamp": "2026-06-01T01:20:00",
    "temperature": 37.04,
    "battery": 61.83,
    "signal_strength": -80.99
  },
  {
    "device_id": "DEV_005",
    "timestamp": "2026-06-01T01:25:00",
    "temperature": 38.41,
    "battery": 61.66,
    "signal_strength": -79.7
  },
  {
    "device_id": "DEV_005",
    "timestamp": "2026-06-01T01:30:00",
    "temperature": 37.14,
    "battery": 61.96,
    "signal_strength": -78.94
  },
  {
    "device_id": "DEV_005",
    "timestamp": "2026-06-01T01:35:00",
    "temperature": 35.95,
    "battery": 62.4,
    "signal_strength": -76.84
  },
  {
    "device_id": "DEV_005",
    "timestamp": "2026-06-01T01:40:00",
    "temperature": 36.25,
    "battery": 61.79,
    "signal_strength": -73.94
  },
  {
    "device_id": "DEV_005",
    "timestamp": "2026-06-01T01:45:00",
    "temperature": 37.1,
    "battery": 61.55,
    "signal_strength": -74.37
  },
  {
    "device_id": "DEV_005",
    "timestamp": "2026-06-01T01:50:00",
    "temperature": 36.71,
    "battery": 61.56,
    "signal_strength": -75.32
  },
  {
    "device_id": "DEV_005",
    "timestamp": "2026-06-01T01:55:00",
    "temperature": 37.76,
    "battery": 62.08,
    "signal_strength": -77.69
  },
  {
    "device_id": "DEV_005",
    "timestamp": "2026-06-01T02:00:00",
    "temperature": 39.14,
    "battery": 62.3,
    "signal_strength": -75.72
  },
  {
    "device_id": "DEV_005",
    "timestamp": "2026-06-01T02:05:00",
    "temperature": 39.76,
    "battery": 62.2,
    "signal_strength": -74.32
  },
  {
    "device_id": "DEV_005",
    "timestamp": "2026-06-01T02:10:00",
    "temperature": 41.16,
    "battery": 61.83,
    "signal_strength": -72.47
  },
  {
    "device_id": "DEV_005",
    "timestamp": "2026-06-01T02:15:00",
    "temperature": 41.27,
    "battery": 61.8,
    "signal_strength": -72.86
  },
  {
    "device_id": "DEV_005",
    "timestamp": "2026-06-01T02:20:00",
    "temperature": 41.96,
    "battery": 61.43,
    "signal_strength": -70.75
  },
  {
    "device_id": "DEV_005",
    "timestamp": "2026-06-01T02:25:00",
    "temperature": 42.95,
    "battery": 60.77,
    "signal_strength": -68.46
  },
  {
    "device_id": "DEV_005",
    "timestamp": "2026-06-01T02:30:00",
    "temperature": 42.18,
    "battery": 60.71,
    "signal_strength": -67.8
  },
  {
    "device_id": "DEV_005",
    "timestamp": "2026-06-01T02:35:00",
    "temperature": 41.82,
    "battery": 59.96,
    "signal_strength": -65.69
  },
  {
    "device_id": "DEV_005",
    "timestamp": "2026-06-01T02:40:00",
    "temperature": 40.87,
    "battery": 59.5,
    "signal_strength": -63.9
  },
  {
    "device_id": "DEV_005",
    "timestamp": "2026-06-01T02:45:00",
    "temperature": 40.39,
    "battery": 60.11,
    "signal_strength": -62.69
  },
  {
    "device_id": "DEV_005",
    "timestamp": "2026-06-01T02:50:00",
    "temperature": 39.72,
    "battery": 59.33,
    "signal_strength": -60.0
  },
  {
    "device_id": "DEV_005",
    "timestamp": "2026-06-01T02:55:00",
    "temperature": 38.48,
    "battery": 59.68,
    "signal_strength": -60.07
  },
  {
    "device_id": "DEV_005",
    "timestamp": "2026-06-01T03:00:00",
    "temperature": 39.25,
    "battery": 59.98,
    "signal_strength": -59.19
  },
  {
    "device_id": "DEV_005",
    "timestamp": "2026-06-01T03:05:00",
    "temperature": 39.22,
    "battery": 60.45,
    "signal_strength": -61.63
  },
  {
    "device_id": "DEV_005",
    "timestamp": "2026-06-01T03:10:00",
    "temperature": 38.38,
    "battery": 60.76,
    "signal_strength": -62.79
  },
  {
    "device_id": "DEV_005",
    "timestamp": "2026-06-01T03:15:00",
    "temperature": 38.62,
    "battery": 60.72,
    "signal_strength": -62.6
  },
  {
    "device_id": "DEV_004",
    "timestamp": "2026-06-01T03:30:00",
    "battery": 70.0,
    "signal_strength": -60.0
  },
  {
    "device_id": "DEV_005",
    "timestamp": "2026-06-01T03:35:00",
    "temperature": 35.0,
    "signal_strength": -60.0
  },
  {
    "device_id": "DEV_003",
    "timestamp": "2026-06-01T03:40:00",
    "temperature": 35.0,
    "battery": 70.0
  },
  {
    "device_id": "DEV_003",
    "timestamp": "2026-06-01T03:45:00",
    "signal_strength": -60.0
  },
  {
    "device_id": "DEV_004",
    "timestamp": "2026-06-01T03:50:00",
    "temperature": 35.0
  },
  {
    "timestamp": "2026-06-01T03:55:00",
    "temperature": 35.0,
    "battery": 70.0,
    "signal_strength": -60.0
  },
  {
    "device_id": "DEV_003",
    "timestamp": "2026-06-01T04:20:00",
    "temperature": 150.0,
    "battery": 50.0,
    "signal_strength": -60.0
  },
  {
    "device_id": "DEV_003",
    "timestamp": "2026-06-01T04:25:00",
    "temperature": -100.0,
    "battery": 50.0,
    "signal_strength": -60.0
  },
  {
    "device_id": "DEV_002",
    "timestamp": "2026-06-01T04:30:00",
    "temperature": 40.0,
    "battery": -10.0,
    "signal_strength": -60.0
  },
  {
    "device_id": "DEV_001",
    "timestamp": "2026-06-01T04:35:00",
    "temperature": 40.0,
    "battery": 150.0,
    "signal_strength": -60.0
  },
  {
    "device_id": "DEV_002",
    "timestamp": "2026-06-01T04:40:00",
    "temperature": 40.0,
    "battery": 50.0,
    "signal_strength": 50.0
  },
  {
    "device_id": "DEV_003",
    "timestamp": "2026-06-01T04:45:00",
    "temperature": 40.0,
    "battery": 50.0,
    "signal_strength": -200.0
  },
  {
    "device_id": "DEV_001",
    "timestamp": "2026-06-01T00:35:00",
    "temperature": 51.79,
    "battery": 57.9,
    "signal_strength": -69.62
  },
  {
    "device_id": "DEV_002",
    "timestamp": "2026-06-01T00:35:00",
    "temperature": 47.63,
    "battery": 58.52,
    "signal_strength": -67.15
  },
  {
    "device_id": "DEV_001",
    "timestamp": "2026-06-01T02:50:00",
    "temperature": 54.97,
    "battery": 53.98,
    "signal_strength": -63.07
  },
  {
    "device_id": "DEV_002",
    "timestamp": "2026-06-01T00:40:00",
    "temperature": 49.12,
    "battery": 58.76,
    "signal_strength": -67.52
  },
  {
    "device_id": "DEV_002",
    "timestamp": "2026-05-31T15:40:00",
    "temperature": 35.0,
    "battery": 70.0,
    "signal_strength": -60.0
  },
  {
    "device_id": "DEV_002",
    "timestamp": "2026-05-31T15:50:00",
    "temperature": 35.0,
    "battery": 70.0,
    "signal_strength": -60.0
  },
  {
    "device_id": "DEV_002",
    "timestamp": "2026-05-31T16:00:00",
    "temperature": 35.0,
    "battery": 70.0,
    "signal_strength": -60.0
  },
  {
    "device_id": "DEV_004",
    "timestamp": "2026-05-31T16:10:00",
    "temperature": 35.0,
    "battery": 70.0,
    "signal_strength": -60.0
  },
  "GARBAGE_LINE_$$##@@",
  "null",
  {
    "device_id": null,
    "timestamp": "not-a-timestamp",
    "temperature": "hot",
    "battery": "full",
    "signal_strength": "strong"
  },
  {
    "device_id": "DEV_003",
    "timestamp": "not-a-timestamp",
    "temperature": "N/A",
    "battery": null,
    "signal_strength": -60.0
  },
  {
    "device_id": "DEV_001",
    "timestamp": "2026-06-02T09:20:00",
    "temperature": 78.0,
    "battery": 60.0,
    "signal_strength": -50.0
  },
  {
    "device_id": "DEV_002",
    "timestamp": "2026-06-02T09:25:00",
    "temperature": 40.0,
    "battery": 5.0,
    "signal_strength": -55.0
  },
  {
    "device_id": "DEV_003",
    "timestamp": "2026-06-01T01:40:00",
    "temperature": 25.0,
    "battery": 90.0,
    "signal_strength": -50.0
  },
  {
    "device_id": "DEV_003",
    "timestamp": "2026-06-01T01:45:00",
    "temperature": 55.0,
    "battery": 90.0,
    "signal_strength": -50.0
  },
  {
    "device_id": "DEV_004",
    "timestamp": "2026-06-01T01:40:00",
    "temperature": 30.0,
    "battery": 85.0,
    "signal_strength": -55.0
  },
  {
    "device_id": "DEV_004",
    "timestamp": "2026-06-01T01:45:00",
    "temperature": 30.0,
    "battery": 50.0,
    "signal_strength": -55.0
  }
]